xfers/__init__.py
xfers/api_resource.py
xfers/error.py
xfers/xfbankaccount.py
xfers/xfcard.py
xfers/xfcharge.py
xfers/xfconnect.py
xfers/xfintent.py
xfers/xfpayout.py
xfers/xfuser.py
xfers-1.4.1.dist-info/DESCRIPTION.rst
xfers-1.4.1.dist-info/METADATA
xfers-1.4.1.dist-info/RECORD
xfers-1.4.1.dist-info/WHEEL
xfers-1.4.1.dist-info/metadata.json
xfers-1.4.1.dist-info/top_level.txt
