Metadata-Version: 2.0
Name: xfers
Version: 1.4.1
Summary: Xfers python bindings
Home-page: https://github.com/Xfers/xfers-python
Author: Xfers
Author-email: support@xfers.io
License: MIT
Keywords: payments,xfers
Platform: UNKNOWN
Classifier: Intended Audience :: Developers
Classifier: License :: OSI Approved :: MIT License
Classifier: Operating System :: OS Independent
Classifier: Programming Language :: Python
Classifier: Programming Language :: Python :: 2
Classifier: Programming Language :: Python :: 2.6
Classifier: Programming Language :: Python :: 2.7
Classifier: Programming Language :: Python :: Implementation :: PyPy
Classifier: Topic :: Software Development :: Libraries :: Python Modules
Requires-Dist: requests (>=2.18.1)
Requires-Dist: pyopenssl (>=17.1.0)
